{
  "Routes": [
    {
      "DownstreamPathTemplate": "/api/Users/GetUserList",
      "DownstreamScheme": "https",
      "DownstreamHostAndPorts": [
        {
          "Host": "localhost",
          "Port": 7024
        }
      ],
      "UpstreamPathTemplate": "/User/GetList",
      "UpstreamHttpMethod": [ "Get" ]
    },
    {
      "DownstreamPathTemplate": "/api/Users/UserAdd",
      "DownstreamScheme": "https",
      "DownstreamHostAndPorts": [
        {
          "Host": "localhost",
          "Port": 7024
        }
      ],
      "UpstreamPathTemplate": "/User/UserAdd",
      "UpstreamHttpMethod": [ "Post" ]
    },
    {
      "DownstreamPathTemplate": "/api/Users/UserUpdate",
      "DownstreamScheme": "https",
      "DownstreamHostAndPorts": [
        {
          "Host": "localhost",
          "Port": 7024
        }
      ],
      "UpstreamPathTemplate": "/User/UserUpdate",
      "UpstreamHttpMethod": [ "Post" ]
    },
    {
      "DownstreamPathTemplate": "/api/Users/UserDelete",
      "DownstreamScheme": "https",
      "DownstreamHostAndPorts": [
        {
          "Host": "localhost",
          "Port": 7024
        }
      ],
      "UpstreamPathTemplate": "/User/UserDelete",
      "UpstreamHttpMethod": [ "Post" ]
    },
    {
      "DownstreamPathTemplate": "/api/Users/GetUserAuthentication",
      "DownstreamScheme": "https",
      "DownstreamHostAndPorts": [
        {
          "Host": "localhost",
          "Port": 7024
        }
      ],
      "UpstreamPathTemplate": "/User/GetUserAuthentication",
      "UpstreamHttpMethod": [ "Post" ]
    },
    {
      "DownstreamPathTemplate": "/api/Authentication/UserAuthentication",
      "DownstreamScheme": "https",
      "DownstreamHostAndPorts": [
        {
          "Host": "localhost",
          "Port": 7067
        }
      ],
      "UpstreamPathTemplate": "/Authentication/UserAuthentication",
      "UpstreamHttpMethod": [ "Post" ]
    },
    {
      "DownstreamPathTemplate": "/api/UserManagement/UserAdd",
      "DownstreamScheme": "https",
      "DownstreamHostAndPorts": [
        {
          "Host": "localhost",
          "Port": 7075
        }
      ],
      "UpstreamPathTemplate": "/UserManagement/UserAdd",
      "UpstreamHttpMethod": [ "Post" ]
    },
    {
      "DownstreamPathTemplate": "/api/UserManagement/UserDelete",
      "DownstreamScheme": "https",
      "DownstreamHostAndPorts": [
        {
          "Host": "localhost",
          "Port": 7075
        }
      ],
      "UpstreamPathTemplate": "/UserManagement/UserDelete",
      "UpstreamHttpMethod": [ "Post" ]
    },
    {
      "DownstreamPathTemplate": "/api/UserManagement/UserUpdate",
      "DownstreamScheme": "https",
      "DownstreamHostAndPorts": [
        {
          "Host": "localhost",
          "Port": 7075
        }
      ],
      "UpstreamPathTemplate": "/UserManagement/UserUpdate",
      "UpstreamHttpMethod": [ "Post" ]
    }

  ],
  "GlobalConfiguration": {}
}